Metadata-Version: 2.1
Name: AegosCH
Version: 0.3
Summary: Checking emails for tiktok or instagram .
Author: AegosCH
Author-email: syakkml@gmail.com
Classifier: Programming Language :: Python :: 3
Classifier: Operating System :: OS Independent
Classifier: License :: OSI Approved :: MIT License
